{"title":"Combined feed","url":"https://FASHIONCORD.github.io/harpersbazaar/all.xml","elements":[{"title":"2023 SS 밀란 패션위크 하이라이츠 1 (하퍼스바자 코리아 ─ 패션)","contents":"<!-- 2022-01-07 수정 -->\n                            <div class=\"imgbox Thumb455\" style=\"background-image: url('https://image.jtbcplus.kr/data/contents/jam_photo/202209/30/91c7179d-4c47-48ca-8e26-dff7ba0a612c.jpg');\">\n                                <a href=\"/article/71240\">\n                                    <img alt=\"\" src=\"\">\n                                </a>\n                            </div>\n                            <!-- <div class=\"imgbox\">\n                                <a href=\"/article/\">\n                                    <img src=\"\" alt=\"\">\n                                </a>\n                            </div> -->\n                            <div class=\"textbox\">\n                                                        <em class=\"title\">\n                                    <a href=\"/article/71240\">\n                                        2023 SS 밀란 패션위크 하이라이츠 1                                    </a>\n                                </em>\n                                <p class=\"excerpt\">재기발랄한 볼거리로 가득했던 밀란패션위크.   </p>\n                            </div>","link":"https://www.harpersbazaar.co.kr/article/71240","retrieved":1664722928305,"image":"https://image.jtbcplus.kr/data/contents/jam_photo/202209/30/91c7179d-4c47-48ca-8e26-dff7ba0a612c.jpg"},{"title":"컬렉션에 불어온 스포티즘 (하퍼스바자 코리아 ─ 패션)","contents":"<!-- 2022-01-07 수정 -->\n                            <div class=\"imgbox Thumb455\" style=\"background-image: url('https://image.jtbcplus.kr/data/contents/jam_photo/202209/30/a5df3311-607b-435c-8aeb-de11852da914.jpg');\">\n                                <a href=\"/article/71205\">\n                                    <img alt=\"\" src=\"\">\n                                </a>\n                            </div>\n                            <!-- <div class=\"imgbox\">\n                                <a href=\"/article/\">\n                                    <img src=\"\" alt=\"\">\n                                </a>\n                            </div> -->\n                            <div class=\"textbox\">\n                                                        <em class=\"title\">\n                                    <a href=\"/article/71205\">\n                                        컬렉션에 불어온 스포티즘                                    </a>\n                                </em>\n                                <p class=\"excerpt\">패션과 스포츠, 전통과 혁신을 결합하는 오니츠카타이거의 2023 S/S 컬렉션.</p>\n                            </div>","link":"https://www.harpersbazaar.co.kr/article/71205","retrieved":1664684869856,"image":"https://image.jtbcplus.kr/data/contents/jam_photo/202209/30/a5df3311-607b-435c-8aeb-de11852da914.jpg"},{"title":"강렬한 모터사이클 재킷을 즐기고 싶다면 이들처럼! (하퍼스바자 코리아 ─ 패션)","contents":"<!-- 2022-01-07 수정 -->\n                            <div class=\"imgbox Thumb455\" style=\"background-image: url('https://image.jtbcplus.kr/data/contents/jam_photo/202209/30/f5d2689f-58be-43ba-8ef0-3d4853ae5f24.jpg');\">\n                                <a href=\"/article/71185\">\n                                    <img alt=\"\" src=\"\">\n                                </a>\n                            </div>\n                            <!-- <div class=\"imgbox\">\n                                <a href=\"/article/\">\n                                    <img src=\"\" alt=\"\">\n                                </a>\n                            </div> -->\n                            <div class=\"textbox\">\n                                                        <em class=\"title\">\n                                    <a href=\"/article/71185\">\n                                        강렬한 모터사이클 재킷을 즐기고 싶다면 이들처럼!                                    </a>\n                                </em>\n                                <p class=\"excerpt\">모터사이클 재킷의 질주가 시작됐다. 오버사이즈에 강렬한 원색, 유니크한 디테일 등 화려한 자태...</p>\n                            </div>","link":"https://www.harpersbazaar.co.kr/article/71185","retrieved":1664550668277,"image":"https://image.jtbcplus.kr/data/contents/jam_photo/202209/30/f5d2689f-58be-43ba-8ef0-3d4853ae5f24.jpg"},{"title":"올가을엔 레그 워머를 신겠어요 (하퍼스바자 코리아 ─ 패션)","contents":"<!-- 2022-01-07 수정 -->\n                            <div class=\"imgbox Thumb455\" style=\"background-image: url('https://image.jtbcplus.kr/data/contents/jam_photo/202209/29/f0e231b7-458b-4d2f-aa27-deb6b3c15815.jpg');\">\n                                <a href=\"/article/71188\">\n                                    <img alt=\"\" src=\"\">\n                                </a>\n                            </div>\n                            <!-- <div class=\"imgbox\">\n                                <a href=\"/article/\">\n                                    <img src=\"\" alt=\"\">\n                                </a>\n                            </div> -->\n                            <div class=\"textbox\">\n                                                        <em class=\"title\">\n                                    <a href=\"/article/71188\">\n                                        올가을엔 레그 워머를 신겠어요                                     </a>\n                                </em>\n                                <p class=\"excerpt\">휑한 종아리는 이제 그만! 화려하게 컴백한 레그 워머 스타일링 비법.</p>\n                            </div>","link":"https://www.harpersbazaar.co.kr/article/71188","retrieved":1664550668280,"image":"https://image.jtbcplus.kr/data/contents/jam_photo/202209/29/f0e231b7-458b-4d2f-aa27-deb6b3c15815.jpg"},{"title":"평범한 바지도 특별하게, 허릿단 접기 (하퍼스바자 코리아 ─ 패션)","contents":"<div class=\"imgbox Thumb455\" style=\"background-image: url('https://image.jtbcplus.kr/data/contents/jam_photo/202209/29/ed24d650-2d45-4c29-9339-a85be5151e30.jpg');\">\n                                <a href=\"/article/71186\">\n                                    <img alt=\"\" src=\"\">\n                                </a>\n                            </div>\n<!--                            <div class=\"imgbox\">-->\n<!--                                <a href=\"/article/--><!--\">-->\n<!--                                    <img src=\"--><!--\" alt=\"--><!--\">-->\n<!--                                </a>-->\n<!--                            </div>-->\n                            <div class=\"textbox\">\n                                                        <em class=\"title\">\n                                    <a href=\"/article/71186\">\n                                        평범한 바지도 특별하게, 허릿단 접기                                     </a>\n                                </em>\n                                <p class=\"excerpt\">평범함을 거부하는 그녀들의 스타일링 비법! 허릿단을 접은 바지의 매력.</p>\n                            </div>","link":"https://www.harpersbazaar.co.kr/article/71186","retrieved":1664529482449,"image":"https://image.jtbcplus.kr/data/contents/jam_photo/202209/29/ed24d650-2d45-4c29-9339-a85be5151e30.jpg"},{"title":"톱모델 한혜진이 20년간 지킨다는 모닝 루틴? (하퍼스바자 코리아 ─ 패션)","contents":"<div class=\"imgbox Thumb455\" style=\"background-image: url('https://image.jtbcplus.kr/data/contents/jam_photo/202209/29/91981668-e50f-46d3-8450-375601303b4d.jpg');\">\n                                <a href=\"/article/71137\">\n                                    <img alt=\"\" src=\"\">\n                                </a>\n                            </div>\n<!--                            <div class=\"imgbox\">-->\n<!--                                <a href=\"/article/--><!--\">-->\n<!--                                    <img src=\"--><!--\" alt=\"--><!--\">-->\n<!--                                </a>-->\n<!--                            </div>-->\n                            <div class=\"textbox\">\n                                                        <em class=\"title\">\n                                    <a href=\"/article/71137\">\n                                        톱모델 한혜진이 20년간 지킨다는 모닝 루틴?                                    </a>\n                                </em>\n                                <p class=\"excerpt\">톱모델은 하루아침에 만들어지지 않는다. 한혜진이 하루도 거르지 않는다는 모닝 루틴!</p>\n                            </div>","link":"https://www.harpersbazaar.co.kr/article/71137","retrieved":1664464146176,"image":"https://image.jtbcplus.kr/data/contents/jam_photo/202209/29/91981668-e50f-46d3-8450-375601303b4d.jpg"},{"title":"2023 S/S 런던패션위크의 다채로운 하이라이츠! (하퍼스바자 코리아 ─ 패션)","contents":"<div class=\"imgbox Thumb455\" style=\"background-image: url('https://image.jtbcplus.kr/data/contents/jam_photo/202209/30/058cd91d-6f5f-411d-a2f4-c70a6c08f69f.jpg');\">\n                                <a href=\"/article/71128\">\n                                    <img alt=\"\" src=\"\">\n                                </a>\n                            </div>\n<!--                            <div class=\"imgbox\">-->\n<!--                                <a href=\"/article/--><!--\">-->\n<!--                                    <img src=\"--><!--\" alt=\"--><!--\">-->\n<!--                                </a>-->\n<!--                            </div>-->\n                            <div class=\"textbox\">\n                                                        <em class=\"title\">\n                                    <a href=\"/article/71128\">\n                                        2023 S/S 런던패션위크의 다채로운 하이라이츠!                                    </a>\n                                </em>\n                                <p class=\"excerpt\">신선함으로 가득했던 런던패션위크 속 주목해야할 10개의 브랜드!</p>\n                            </div>","link":"https://www.harpersbazaar.co.kr/article/71128","retrieved":1664529482450,"image":"https://image.jtbcplus.kr/data/contents/jam_photo/202209/30/058cd91d-6f5f-411d-a2f4-c70a6c08f69f.jpg"},{"title":"구찌 트윈스버그 컬렉션 (하퍼스바자 코리아 ─ 패션)","contents":"<div class=\"imgbox Thumb455\" style=\"background-image: url('https://image.jtbcplus.kr/data/contents/jam_photo/202209/28/ffe237a2-7024-47d1-9308-e5a89bd0ffae.jpg');\">\n                                <a href=\"/article/71090\">\n                                    <img alt=\"\" src=\"\">\n                                </a>\n                            </div>\n<!--                            <div class=\"imgbox\">-->\n<!--                                <a href=\"/article/--><!--\">-->\n<!--                                    <img src=\"--><!--\" alt=\"--><!--\">-->\n<!--                                </a>-->\n<!--                            </div>-->\n                            <div class=\"textbox\">\n                                                        <em class=\"title\">\n                                    <a href=\"/article/71090\">\n                                        구찌 트윈스버그 컬렉션                                    </a>\n                                </em>\n                                <p class=\"excerpt\">같은 듯 다른 매력. 구찌 트윈스버그 컬렉션이 공개됐다.</p>\n                            </div>","link":"https://www.harpersbazaar.co.kr/article/71090","retrieved":1664464127425,"image":"https://image.jtbcplus.kr/data/contents/jam_photo/202209/28/ffe237a2-7024-47d1-9308-e5a89bd0ffae.jpg"},{"title":"진영의 요즘 향수, 나르시소 로드리게즈 (하퍼스바자 코리아 ─ 뷰티)","contents":"<!-- 2022-01-07 수정 -->\n                            <div class=\"imgbox Thumb455\" style=\"background-image: url('https://image.jtbcplus.kr/data/contents/jam_photo/202209/30/812dcf0e-fe18-45b2-a859-32fcadde2254.jpg');\">\n                                <a href=\"/article/71218\">\n                                    <img alt=\"\" src=\"\">\n                                </a>\n                            </div>\n                            <!-- <div class=\"imgbox\">\n                                <a href=\"/article/\">\n                                    <img src=\"\" alt=\"\">\n                                </a>\n                            </div> -->\n                            <div class=\"textbox\">\n                                                        <em class=\"title\">\n                                    <a href=\"/article/71218\">\n                                        진영의 요즘 향수, 나르시소 로드리게즈                                    </a>\n                                </em>\n                                <p class=\"excerpt\">순수함과 관능의 빛. 진영에게 스며든 ‘나르시소 로드리게즈’의 강렬한 찰나. </p>\n                            </div>","link":"https://www.harpersbazaar.co.kr/article/71218","retrieved":1664722945845,"image":"https://image.jtbcplus.kr/data/contents/jam_photo/202209/30/812dcf0e-fe18-45b2-a859-32fcadde2254.jpg"},{"title":"발색도 좋고 촉촉한 매트립을 찾고 있다면? (하퍼스바자 코리아 ─ 뷰티)","contents":"<!-- 2022-01-07 수정 -->\n                            <div class=\"imgbox Thumb455\" style=\"background-image: url('https://image.jtbcplus.kr/data/contents/jam_photo/202209/30/95885bbe-d527-4174-953b-2499515ce987.jpg');\">\n                                <a href=\"/article/71183\">\n                                    <img alt=\"\" src=\"\">\n                                </a>\n                            </div>\n                            <!-- <div class=\"imgbox\">\n                                <a href=\"/article/\">\n                                    <img src=\"\" alt=\"\">\n                                </a>\n                            </div> -->\n                            <div class=\"textbox\">\n                                                        <em class=\"title\">\n                                    <a href=\"/article/71183\">\n                                        발색도 좋고 촉촉한 매트립을 찾고 있다면?                                    </a>\n                                </em>\n                                <p class=\"excerpt\">매트의 진화는 오늘도 계속된다. 독보적인 색감과 사용감을 위해 갈고 닦은 실력을 여지없이 뽐...</p>\n                            </div>","link":"https://www.harpersbazaar.co.kr/article/71183","retrieved":1664550684956,"image":"https://image.jtbcplus.kr/data/contents/jam_photo/202209/30/95885bbe-d527-4174-953b-2499515ce987.jpg"},{"title":"과자 먹으면서 10KG 감량했다고? #다이어트두부과자 (하퍼스바자 코리아 ─ 뷰티)","contents":"<!-- 2022-01-07 수정 -->\n                            <div class=\"imgbox Thumb455\" style=\"background-image: url('https://image.jtbcplus.kr/data/contents/jam_photo/202209/29/c0be6ebb-b9de-4e1a-83aa-ca6d98109ef6.jpg');\">\n                                <a href=\"/article/71209\">\n                                    <img alt=\"\" src=\"\">\n                                </a>\n                            </div>\n                            <!-- <div class=\"imgbox\">\n                                <a href=\"/article/\">\n                                    <img src=\"\" alt=\"\">\n                                </a>\n                            </div> -->\n                            <div class=\"textbox\">\n                                                        <em class=\"title\">\n                                    <a href=\"/article/71209\">\n                                        과자 먹으면서 10KG 감량했다고? #다이어트두부과자                                    </a>\n                                </em>\n                                <p class=\"excerpt\">다이어터도 맘 놓고 즐기는 고단백 두부 과자 레시피! </p>\n                            </div>","link":"https://www.harpersbazaar.co.kr/article/71209","retrieved":1664550684958,"image":"https://image.jtbcplus.kr/data/contents/jam_photo/202209/29/c0be6ebb-b9de-4e1a-83aa-ca6d98109ef6.jpg"},{"title":"다이어터들의 식단 치트키 #토르티야레시피 (하퍼스바자 코리아 ─ 뷰티)","contents":"<!-- 2022-01-07 수정 -->\n                            <div class=\"imgbox Thumb455\" style=\"background-image: url('https://image.jtbcplus.kr/data/contents/jam_photo/202209/29/de3fe2f9-c85e-4af7-8100-45b13f30bd8d.jpg');\">\n                                <a href=\"/article/71207\">\n                                    <img alt=\"\" src=\"\">\n                                </a>\n                            </div>\n                            <!-- <div class=\"imgbox\">\n                                <a href=\"/article/\">\n                                    <img src=\"\" alt=\"\">\n                                </a>\n                            </div> -->\n                            <div class=\"textbox\">\n                                                        <em class=\"title\">\n                                    <a href=\"/article/71207\">\n                                        다이어터들의 식단 치트키 #토르티야레시피                                    </a>\n                                </em>\n                                <p class=\"excerpt\">저탄수 식단의 만능 치트키! 다이어트 좋은 토르티야 레시피.</p>\n                            </div>","link":"https://www.harpersbazaar.co.kr/article/71207","retrieved":1664513530168,"image":"https://image.jtbcplus.kr/data/contents/jam_photo/202209/29/de3fe2f9-c85e-4af7-8100-45b13f30bd8d.jpg"},{"title":"15년 발레 경력, 르세라핌의 카즈하가 여전히 하는 스트레칭 (하퍼스바자 코리아 ─ 뷰티)","contents":"<div class=\"imgbox Thumb455\" style=\"background-image: url('https://image.jtbcplus.kr/data/contents/jam_photo/202209/29/091947d4-39c9-4f43-8dae-2eff55ff7474.jpg');\">\n                                <a href=\"/article/71184\">\n                                    <img alt=\"\" src=\"\">\n                                </a>\n                            </div>\n<!--                            <div class=\"imgbox\">-->\n<!--                                <a href=\"/article/--><!--\">-->\n<!--                                    <img src=\"--><!--\" alt=\"--><!--\">-->\n<!--                                </a>-->\n<!--                            </div>-->\n                            <div class=\"textbox\">\n                                                        <em class=\"title\">\n                                    <a href=\"/article/71184\">\n                                        15년 발레 경력, 르세라핌의 카즈하가 여전히 하는 스트레칭                                    </a>\n                                </em>\n                                <p class=\"excerpt\">뭉친 근육을 밀어주고 눌러주고! 카즈하가 발레를 하며 익힌 스트레칭 도구들과 운동 팁을 소개...</p>\n                            </div>","link":"https://www.harpersbazaar.co.kr/article/71184","retrieved":1664529500010,"image":"https://image.jtbcplus.kr/data/contents/jam_photo/202209/29/091947d4-39c9-4f43-8dae-2eff55ff7474.jpg"},{"title":"소희가 일주일 내내 먹는 샐러드 레시피 (하퍼스바자 코리아 ─ 뷰티)","contents":"<div class=\"imgbox Thumb455\" style=\"background-image: url('https://image.jtbcplus.kr/data/contents/jam_photo/202209/29/c3f440cd-b671-4750-8a43-c3d78df42ca6.jpg');\">\n                                <a href=\"/article/71179\">\n                                    <img alt=\"\" src=\"\">\n                                </a>\n                            </div>\n<!--                            <div class=\"imgbox\">-->\n<!--                                <a href=\"/article/--><!--\">-->\n<!--                                    <img src=\"--><!--\" alt=\"--><!--\">-->\n<!--                                </a>-->\n<!--                            </div>-->\n                            <div class=\"textbox\">\n                                                        <em class=\"title\">\n                                    <a href=\"/article/71179\">\n                                        소희가 일주일 내내 먹는 샐러드 레시피                                    </a>\n                                </em>\n                                <p class=\"excerpt\">배달 식단부터 촬영날 식단까지 추천!</p>\n                            </div>","link":"https://www.harpersbazaar.co.kr/article/71179","retrieved":1664513447902,"image":"https://image.jtbcplus.kr/data/contents/jam_photo/202209/29/c3f440cd-b671-4750-8a43-c3d78df42ca6.jpg"},{"title":"톱모델 한혜진이 20년간 지킨다는 모닝 루틴? (하퍼스바자 코리아 ─ 뷰티)","contents":"<div class=\"imgbox Thumb455\" style=\"background-image: url('https://image.jtbcplus.kr/data/contents/jam_photo/202209/29/91981668-e50f-46d3-8450-375601303b4d.jpg');\">\n                                <a href=\"/article/71137\">\n                                    <img alt=\"\" src=\"\">\n                                </a>\n                            </div>\n<!--                            <div class=\"imgbox\">-->\n<!--                                <a href=\"/article/--><!--\">-->\n<!--                                    <img src=\"--><!--\" alt=\"--><!--\">-->\n<!--                                </a>-->\n<!--                            </div>-->\n                            <div class=\"textbox\">\n                                                        <em class=\"title\">\n                                    <a href=\"/article/71137\">\n                                        톱모델 한혜진이 20년간 지킨다는 모닝 루틴?                                    </a>\n                                </em>\n                                <p class=\"excerpt\">톱모델은 하루아침에 만들어지지 않는다. 한혜진이 하루도 거르지 않는다는 모닝 루틴!</p>\n                            </div>","link":"https://www.harpersbazaar.co.kr/article/71137","retrieved":1664464146176,"image":"https://image.jtbcplus.kr/data/contents/jam_photo/202209/29/91981668-e50f-46d3-8450-375601303b4d.jpg"},{"title":"톱모델 한혜진이 급찐살 뺄 때 한다는 15분 운동? (하퍼스바자 코리아 ─ 뷰티)","contents":"<div class=\"imgbox Thumb455\" style=\"background-image: url('https://image.jtbcplus.kr/data/contents/jam_photo/202209/29/5efb04f2-0904-4049-8bda-5a3dd0578014.jpg');\">\n                                <a href=\"/article/71094\">\n                                    <img alt=\"\" src=\"\">\n                                </a>\n                            </div>\n<!--                            <div class=\"imgbox\">-->\n<!--                                <a href=\"/article/--><!--\">-->\n<!--                                    <img src=\"--><!--\" alt=\"--><!--\">-->\n<!--                                </a>-->\n<!--                            </div>-->\n                            <div class=\"textbox\">\n                                                        <em class=\"title\">\n                                    <a href=\"/article/71094\">\n                                        톱모델 한혜진이 급찐살 뺄 때 한다는 15분 운동?                                    </a>\n                                </em>\n                                <p class=\"excerpt\">바빠서 운동 못 한다는 핑계는 안 통한다. 무서운 속도로 살이 빠진다는 초속 홈트! </p>\n                            </div>","link":"https://www.harpersbazaar.co.kr/article/71094","retrieved":1664377906671,"image":"https://image.jtbcplus.kr/data/contents/jam_photo/202209/29/5efb04f2-0904-4049-8bda-5a3dd0578014.jpg"},{"title":"꽃보다 뉴진스(NewJeans) <하퍼스 바자> 통해 디올 패션 & 뷰티와 함께 한 화보 공개! (하퍼스바자 코리아 ─ 셀레브리티)","contents":"<!-- 2022-01-07 수정 -->\n                            <div class=\"imgbox Thumb455\" style=\"background-image: url('https://image.jtbcplus.kr/data/contents/jam_photo/202209/29/686f772e-7812-4860-9851-8640b49b5cdb.jpg');\">\n                                <a href=\"/article/71151\">\n                                    <img alt=\"\" src=\"\">\n                                </a>\n                            </div>\n                            <!-- <div class=\"imgbox\">\n                                <a href=\"/article/\">\n                                    <img src=\"\" alt=\"\">\n                                </a>\n                            </div> -->\n                            <div class=\"textbox\">\n                                                        <em class=\"title\">\n                                    <a href=\"/article/71151\">\n                                        꽃보다 뉴진스(NewJeans) &lt;하퍼스 바자&gt; 통해 디올 패션 &amp; 뷰티와 함께 한 화보 공개!                                    </a>\n                                </em>\n                                <p class=\"excerpt\">“현 시대의 가장 핫한 패션 아이콘다운 행보”</p>\n                            </div>","link":"https://www.harpersbazaar.co.kr/article/71151","retrieved":1664722979322,"image":"https://image.jtbcplus.kr/data/contents/jam_photo/202209/29/686f772e-7812-4860-9851-8640b49b5cdb.jpg"},{"title":"김혜수, 조인성을 사로잡은 한효주의 #브라운치즈 디저트? (하퍼스바자 코리아 ─ 셀레브리티)","contents":"<!-- 2022-01-07 수정 -->\n                            <div class=\"imgbox Thumb455\" style=\"background-image: url('https://image.jtbcplus.kr/data/contents/jam_photo/202209/29/b65ba1de-33e0-490c-901b-d5fc31fcb389.jpg');\">\n                                <a href=\"/article/71138\">\n                                    <img alt=\"\" src=\"\">\n                                </a>\n                            </div>\n                            <!-- <div class=\"imgbox\">\n                                <a href=\"/article/\">\n                                    <img src=\"\" alt=\"\">\n                                </a>\n                            </div> -->\n                            <div class=\"textbox\">\n                                                        <em class=\"title\">\n                                    <a href=\"/article/71138\">\n                                        김혜수, 조인성을 사로잡은 한효주의 #브라운치즈 디저트?                                     </a>\n                                </em>\n                                <p class=\"excerpt\">한번 맛보면 탈출구는 없다. 단짠단짠 묘한 매력의 브라운 치즈 활용 레시피! </p>\n                            </div>","link":"https://www.harpersbazaar.co.kr/article/71138","retrieved":1664513547286,"image":"https://image.jtbcplus.kr/data/contents/jam_photo/202209/29/b65ba1de-33e0-490c-901b-d5fc31fcb389.jpg"},{"title":"톱모델 한혜진이 20년간 지킨다는 모닝 루틴? (하퍼스바자 코리아 ─ 셀레브리티)","contents":"<!-- 2022-01-07 수정 -->\n                            <div class=\"imgbox Thumb455\" style=\"background-image: url('https://image.jtbcplus.kr/data/contents/jam_photo/202209/29/91981668-e50f-46d3-8450-375601303b4d.jpg');\">\n                                <a href=\"/article/71137\">\n                                    <img alt=\"\" src=\"\">\n                                </a>\n                            </div>\n                            <!-- <div class=\"imgbox\">\n                                <a href=\"/article/\">\n                                    <img src=\"\" alt=\"\">\n                                </a>\n                            </div> -->\n                            <div class=\"textbox\">\n                                                        <em class=\"title\">\n                                    <a href=\"/article/71137\">\n                                        톱모델 한혜진이 20년간 지킨다는 모닝 루틴?                                    </a>\n                                </em>\n                                <p class=\"excerpt\">톱모델은 하루아침에 만들어지지 않는다. 한혜진이 하루도 거르지 않는다는 모닝 루틴!</p>\n                            </div>","link":"https://www.harpersbazaar.co.kr/article/71137","retrieved":1664464146176,"image":"https://image.jtbcplus.kr/data/contents/jam_photo/202209/29/91981668-e50f-46d3-8450-375601303b4d.jpg"},{"title":"남궁민, '11세 연하+7년 연애' 진아름과 10월 7일 결혼 (하퍼스바자 코리아 ─ 셀레브리티)","contents":"<!-- 2022-01-07 수정 -->\n                            <div class=\"imgbox Thumb455\" style=\"background-image: url('https://image.jtbcplus.kr/data/contents/jam_photo/202209/28/44e05090-b439-4e30-b1c7-e52e3834f3c9.jpg');\">\n                                <a href=\"/article/71104\">\n                                    <img alt=\"\" src=\"\">\n                                </a>\n                            </div>\n                            <!-- <div class=\"imgbox\">\n                                <a href=\"/article/\">\n                                    <img src=\"\" alt=\"\">\n                                </a>\n                            </div> -->\n                            <div class=\"textbox\">\n                                                        <em class=\"title\">\n                                    <a href=\"/article/71104\">\n                                        남궁민, '11세 연하+7년 연애' 진아름과 10월 7일 결혼                                    </a>\n                                </em>\n                                <p class=\"excerpt\">신라호텔에서 비공개 결혼식.. 사회는 배우 정문성</p>\n                            </div>","link":"https://www.harpersbazaar.co.kr/article/71104","retrieved":1664442980834,"image":"https://image.jtbcplus.kr/data/contents/jam_photo/202209/28/44e05090-b439-4e30-b1c7-e52e3834f3c9.jpg"},{"title":"톱모델 한혜진이 급찐살 뺄 때 한다는 15분 운동? (하퍼스바자 코리아 ─ 셀레브리티)","contents":"<div class=\"imgbox Thumb455\" style=\"background-image: url('https://image.jtbcplus.kr/data/contents/jam_photo/202209/29/5efb04f2-0904-4049-8bda-5a3dd0578014.jpg');\">\n                                <a href=\"/article/71094\">\n                                    <img alt=\"\" src=\"\">\n                                </a>\n                            </div>\n<!--                            <div class=\"imgbox\">-->\n<!--                                <a href=\"/article/--><!--\">-->\n<!--                                    <img src=\"--><!--\" alt=\"--><!--\">-->\n<!--                                </a>-->\n<!--                            </div>-->\n                            <div class=\"textbox\">\n                                                        <em class=\"title\">\n                                    <a href=\"/article/71094\">\n                                        톱모델 한혜진이 급찐살 뺄 때 한다는 15분 운동?                                    </a>\n                                </em>\n                                <p class=\"excerpt\">바빠서 운동 못 한다는 핑계는 안 통한다. 무서운 속도로 살이 빠진다는 초속 홈트! </p>\n                            </div>","link":"https://www.harpersbazaar.co.kr/article/71094","retrieved":1664377906671,"image":"https://image.jtbcplus.kr/data/contents/jam_photo/202209/29/5efb04f2-0904-4049-8bda-5a3dd0578014.jpg"},{"title":"김나영, 기은세, 오눅도 반한 맛없없 솥밥! (하퍼스바자 코리아 ─ 셀레브리티)","contents":"<div class=\"imgbox Thumb455\" style=\"background-image: url('https://image.jtbcplus.kr/data/contents/jam_photo/202209/29/a6d2e7fd-5272-423e-81d5-8177e6ba2901.jpg');\">\n                                <a href=\"/article/71093\">\n                                    <img alt=\"\" src=\"\">\n                                </a>\n                            </div>\n<!--                            <div class=\"imgbox\">-->\n<!--                                <a href=\"/article/--><!--\">-->\n<!--                                    <img src=\"--><!--\" alt=\"--><!--\">-->\n<!--                                </a>-->\n<!--                            </div>-->\n                            <div class=\"textbox\">\n                                                        <em class=\"title\">\n                                    <a href=\"/article/71093\">\n                                        김나영, 기은세, 오눅도 반한 맛없없 솥밥!                                     </a>\n                                </em>\n                                <p class=\"excerpt\">소문난 미식가, 기은세, 김나영, 오눅의 '맛없없 솥밥' 레시피.</p>\n                            </div>","link":"https://www.harpersbazaar.co.kr/article/71093","retrieved":1664377965316,"image":"https://image.jtbcplus.kr/data/contents/jam_photo/202209/29/a6d2e7fd-5272-423e-81d5-8177e6ba2901.jpg"},{"title":"영화 <늑대사냥>으로 돌아온 정소민의 모든것! #알아두면쓸데있는잡학사전 (하퍼스바자 코리아 ─ 셀레브리티)","contents":"<div class=\"imgbox Thumb455\" style=\"background-image: url('https://image.jtbcplus.kr/data/contents/jam_photo/202209/26/d3231284-109a-456b-8490-bae380ab5314.jpg');\">\n                                <a href=\"/article/71015\">\n                                    <img alt=\"\" src=\"\">\n                                </a>\n                            </div>\n<!--                            <div class=\"imgbox\">-->\n<!--                                <a href=\"/article/--><!--\">-->\n<!--                                    <img src=\"--><!--\" alt=\"--><!--\">-->\n<!--                                </a>-->\n<!--                            </div>-->\n                            <div class=\"textbox\">\n                                                        <em class=\"title\">\n                                    <a href=\"/article/71015\">\n                                        영화 &lt;늑대사냥&gt;으로 돌아온 정소민의 모든것! #알아두면쓸데있는잡학사전                                     </a>\n                                </em>\n                                <p class=\"excerpt\">최근 개봉한 늑대사냥 자랑부터 최근에 펑펑 운 미드까지 모두 다 알려드려요~</p>\n                            </div>","link":"https://www.harpersbazaar.co.kr/article/71015","retrieved":1664377965317,"image":"https://image.jtbcplus.kr/data/contents/jam_photo/202209/26/d3231284-109a-456b-8490-bae380ab5314.jpg"},{"title":"기은세가 고른 마이클 코어스 가을 아이템 착장 베스트 5 (하퍼스바자 코리아 ─ 셀레브리티)","contents":"<div class=\"imgbox Thumb455\" style=\"background-image: url('https://image.jtbcplus.kr/data/contents/jam_photo/202209/27/b4db93ef-e52f-4daf-a519-b448e4b97078.jpg');\">\n                                <a href=\"/article/71008\">\n                                    <img alt=\"\" src=\"\">\n                                </a>\n                            </div>\n<!--                            <div class=\"imgbox\">-->\n<!--                                <a href=\"/article/--><!--\">-->\n<!--                                    <img src=\"--><!--\" alt=\"--><!--\">-->\n<!--                                </a>-->\n<!--                            </div>-->\n                            <div class=\"textbox\">\n                                                        <em class=\"title\">\n                                    <a href=\"/article/71008\">\n                                        기은세가 고른 마이클 코어스 가을 아이템 착장 베스트 5                                    </a>\n                                </em>\n                                <p class=\"excerpt\">마이클 코어스의 2022 가을 시즌과 함께한 기은세.</p>\n                            </div>","link":"https://www.harpersbazaar.co.kr/article/71008","retrieved":1664377965318,"image":"https://image.jtbcplus.kr/data/contents/jam_photo/202209/27/b4db93ef-e52f-4daf-a519-b448e4b97078.jpg"},{"title":"요즘 힙스터들은 #남영동핫플 에서 논다며? (하퍼스바자 코리아 ─ 아트&컬쳐)","contents":"<!-- 2022-01-07 수정 -->\n                            <div class=\"imgbox Thumb455\" style=\"background-image: url('https://image.jtbcplus.kr/data/contents/jam_photo/202209/30/500ed1cb-1b43-4caf-9e48-e77c541f722d.jpg');\">\n                                <a href=\"/article/71252\">\n                                    <img alt=\"\" src=\"\">\n                                </a>\n                            </div>\n                            <!-- <div class=\"imgbox\">\n                                <a href=\"/article/\">\n                                    <img src=\"\" alt=\"\">\n                                </a>\n                            </div> -->\n                            <div class=\"textbox\">\n                                                        <em class=\"title\">\n                                    <a href=\"/article/71252\">\n                                        요즘 힙스터들은 #남영동핫플 에서 논다며?                                    </a>\n                                </em>\n                                <p class=\"excerpt\">남영동이 핫한 이유? 독특한 콘셉트를 지닌 힙플레이스 때문!</p>\n                            </div>","link":"https://www.harpersbazaar.co.kr/article/71252","retrieved":1664723029600,"image":"https://image.jtbcplus.kr/data/contents/jam_photo/202209/30/500ed1cb-1b43-4caf-9e48-e77c541f722d.jpg"},{"title":"유튜버 #오눅 이 강추하는 #뉴욕핫플 은 어디? (하퍼스바자 코리아 ─ 아트&컬쳐)","contents":"<!-- 2022-01-07 수정 -->\n                            <div class=\"imgbox Thumb455\" style=\"background-image: url('https://image.jtbcplus.kr/data/contents/jam_photo/202209/30/bc04cf65-3982-436f-a8e3-fd409b2253a7.jpg');\">\n                                <a href=\"/article/71251\">\n                                    <img alt=\"\" src=\"\">\n                                </a>\n                            </div>\n                            <!-- <div class=\"imgbox\">\n                                <a href=\"/article/\">\n                                    <img src=\"\" alt=\"\">\n                                </a>\n                            </div> -->\n                            <div class=\"textbox\">\n                                                        <em class=\"title\">\n                                    <a href=\"/article/71251\">\n                                        유튜버 #오눅 이 강추하는 #뉴욕핫플 은 어디?                                    </a>\n                                </em>\n                                <p class=\"excerpt\">유튜버 #오눅 이 강추하는 #뉴욕핫플 은 어디?</p>\n                            </div>","link":"https://www.harpersbazaar.co.kr/article/71251","retrieved":1664701925857,"image":"https://image.jtbcplus.kr/data/contents/jam_photo/202209/30/bc04cf65-3982-436f-a8e3-fd409b2253a7.jpg"},{"title":"어차피 대상은 송중기! <옷소매>는 3관왕 [2022 APAN] (하퍼스바자 코리아 ─ 아트&컬쳐)","contents":"<!-- 2022-01-07 수정 -->\n                            <div class=\"imgbox Thumb455\" style=\"background-image: url('https://image.jtbcplus.kr/data/contents/jam_photo/202209/30/4a6a2e35-2d92-4df4-b0a1-dc5689a4231a.jpg');\">\n                                <a href=\"/article/71217\">\n                                    <img alt=\"\" src=\"\">\n                                </a>\n                            </div>\n                            <!-- <div class=\"imgbox\">\n                                <a href=\"/article/\">\n                                    <img src=\"\" alt=\"\">\n                                </a>\n                            </div> -->\n                            <div class=\"textbox\">\n                                                        <em class=\"title\">\n                                    <a href=\"/article/71217\">\n                                        어차피 대상은 송중기! &lt;옷소매&gt;는 3관왕 [2022 APAN]                                    </a>\n                                </em>\n                                <p class=\"excerpt\">빈센조 까사노 변호사님~ 잘 지내고 있나요?</p>\n                            </div>","link":"https://www.harpersbazaar.co.kr/article/71217","retrieved":1664636608104,"image":"https://image.jtbcplus.kr/data/contents/jam_photo/202209/30/4a6a2e35-2d92-4df4-b0a1-dc5689a4231a.jpg"},{"title":"부산비엔날레를 위한 키워드 (하퍼스바자 코리아 ─ 아트&컬쳐)","contents":"<!-- 2022-01-07 수정 -->\n                            <div class=\"imgbox Thumb455\" style=\"background-image: url('https://image.jtbcplus.kr/data/contents/jam_photo/202209/30/a09110fb-a8d6-419a-a3b7-945210e37c05.jpg');\">\n                                <a href=\"/article/71120\">\n                                    <img alt=\"\" src=\"\">\n                                </a>\n                            </div>\n                            <!-- <div class=\"imgbox\">\n                                <a href=\"/article/\">\n                                    <img src=\"\" alt=\"\">\n                                </a>\n                            </div> -->\n                            <div class=\"textbox\">\n                                                        <em class=\"title\">\n                                    <a href=\"/article/71120\">\n                                        부산비엔날레를 위한 키워드                                    </a>\n                                </em>\n                                <p class=\"excerpt\">올해 부산비엔날레의 주제는 ‘물결 위 우리’다. 물결은 요동치는 역사와 사람들의 이동 등 다...</p>\n                            </div>","link":"https://www.harpersbazaar.co.kr/article/71120","retrieved":1664550739688,"image":"https://image.jtbcplus.kr/data/contents/jam_photo/202209/30/a09110fb-a8d6-419a-a3b7-945210e37c05.jpg"},{"title":"영화감독 래리 클락에게서 영감을 받은 공간? #뉴핫플레이스 (하퍼스바자 코리아 ─ 아트&컬쳐)","contents":"<div class=\"imgbox Thumb455\" style=\"background-image: url('https://image.jtbcplus.kr/data/contents/jam_photo/202209/29/48ab1f4f-b905-4c47-9843-212b7ae28015.jpg');\">\n                                <a href=\"/article/71210\">\n                                    <img alt=\"\" src=\"\">\n                                </a>\n                            </div>\n<!--                            <div class=\"imgbox\">-->\n<!--                                <a href=\"/article/--><!--\">-->\n<!--                                    <img src=\"--><!--\" alt=\"--><!--\">-->\n<!--                                </a>-->\n<!--                            </div>-->\n                            <div class=\"textbox\">\n                                                        <em class=\"title\">\n                                    <a href=\"/article/71210\">\n                                        영화감독 래리 클락에게서 영감을 받은 공간? #뉴핫플레이스                                    </a>\n                                </em>\n                                <p class=\"excerpt\">신상러들 모여라! 누구보다 발 빠르게 접수해야 할 뉴 핫플레이스.</p>\n                            </div>","link":"https://www.harpersbazaar.co.kr/article/71210","retrieved":1664550739690,"image":"https://image.jtbcplus.kr/data/contents/jam_photo/202209/29/48ab1f4f-b905-4c47-9843-212b7ae28015.jpg"},{"title":"과자 먹으면서 10KG 감량했다고? #다이어트두부과자 (하퍼스바자 코리아 ─ 아트&컬쳐)","contents":"<div class=\"imgbox Thumb455\" style=\"background-image: url('https://image.jtbcplus.kr/data/contents/jam_photo/202209/29/c0be6ebb-b9de-4e1a-83aa-ca6d98109ef6.jpg');\">\n                                <a href=\"/article/71209\">\n                                    <img alt=\"\" src=\"\">\n                                </a>\n                            </div>\n<!--                            <div class=\"imgbox\">-->\n<!--                                <a href=\"/article/--><!--\">-->\n<!--                                    <img src=\"--><!--\" alt=\"--><!--\">-->\n<!--                                </a>-->\n<!--                            </div>-->\n                            <div class=\"textbox\">\n                                                        <em class=\"title\">\n                                    <a href=\"/article/71209\">\n                                        과자 먹으면서 10KG 감량했다고? #다이어트두부과자                                    </a>\n                                </em>\n                                <p class=\"excerpt\">다이어터도 맘 놓고 즐기는 고단백 두부 과자 레시피! </p>\n                            </div>","link":"https://www.harpersbazaar.co.kr/article/71209","retrieved":1664550684958,"image":"https://image.jtbcplus.kr/data/contents/jam_photo/202209/29/c0be6ebb-b9de-4e1a-83aa-ca6d98109ef6.jpg"},{"title":"백종원이 강추하는 신박한 #샐러리레시피 (하퍼스바자 코리아 ─ 아트&컬쳐)","contents":"<div class=\"imgbox Thumb455\" style=\"background-image: url('https://image.jtbcplus.kr/data/contents/jam_photo/202209/29/cae226c6-537e-450a-be88-44b2ae27e2c0.jpg');\">\n                                <a href=\"/article/71208\">\n                                    <img alt=\"\" src=\"\">\n                                </a>\n                            </div>\n<!--                            <div class=\"imgbox\">-->\n<!--                                <a href=\"/article/--><!--\">-->\n<!--                                    <img src=\"--><!--\" alt=\"--><!--\">-->\n<!--                                </a>-->\n<!--                            </div>-->\n                            <div class=\"textbox\">\n                                                        <em class=\"title\">\n                                    <a href=\"/article/71208\">\n                                        백종원이 강추하는 신박한 #샐러리레시피                                    </a>\n                                </em>\n                                <p class=\"excerpt\">샐러리는 이렇게 먹는 거예요. 신박한 샐러리 레시피! </p>\n                            </div>","link":"https://www.harpersbazaar.co.kr/article/71208","retrieved":1664550739701,"image":"https://image.jtbcplus.kr/data/contents/jam_photo/202209/29/cae226c6-537e-450a-be88-44b2ae27e2c0.jpg"},{"title":"다이어터들의 식단 치트키 #토르티야레시피 (하퍼스바자 코리아 ─ 아트&컬쳐)","contents":"<div class=\"imgbox Thumb455\" style=\"background-image: url('https://image.jtbcplus.kr/data/contents/jam_photo/202209/29/de3fe2f9-c85e-4af7-8100-45b13f30bd8d.jpg');\">\n                                <a href=\"/article/71207\">\n                                    <img alt=\"\" src=\"\">\n                                </a>\n                            </div>\n<!--                            <div class=\"imgbox\">-->\n<!--                                <a href=\"/article/--><!--\">-->\n<!--                                    <img src=\"--><!--\" alt=\"--><!--\">-->\n<!--                                </a>-->\n<!--                            </div>-->\n                            <div class=\"textbox\">\n                                                        <em class=\"title\">\n                                    <a href=\"/article/71207\">\n                                        다이어터들의 식단 치트키 #토르티야레시피                                    </a>\n                                </em>\n                                <p class=\"excerpt\">저탄수 식단의 만능 치트키! 다이어트 좋은 토르티야 레시피.</p>\n                            </div>","link":"https://www.harpersbazaar.co.kr/article/71207","retrieved":1664513530168,"image":"https://image.jtbcplus.kr/data/contents/jam_photo/202209/29/de3fe2f9-c85e-4af7-8100-45b13f30bd8d.jpg"},{"title":"20인의 미식 큐레이터가 엄선한 서울 채식 레스토랑 50 (하퍼스바자 코리아 ─ 라이프스타일)","contents":"<!-- 2022-01-07 수정 -->\n                            <div class=\"imgbox Thumb455\" style=\"background-image: url('https://image.jtbcplus.kr/data/contents/jam_photo/202209/30/99275adb-c24b-4411-8d23-19f3f83a0f26.jpg');\">\n                                <a href=\"/article/71239\">\n                                    <img alt=\"\" src=\"\">\n                                </a>\n                            </div>\n                            <!-- <div class=\"imgbox\">\n                                <a href=\"/article/\">\n                                    <img src=\"\" alt=\"\">\n                                </a>\n                            </div> -->\n                            <div class=\"textbox\">\n                                                        <em class=\"title\">\n                                    <a href=\"/article/71239\">\n                                        20인의 미식 큐레이터가 엄선한 서울 채식 레스토랑 50                                    </a>\n                                </em>\n                                <p class=\"excerpt\">믿고 먹는 서울의 채식 맛집</p>\n                            </div>","link":"https://www.harpersbazaar.co.kr/article/71239","retrieved":1664550757445,"image":"https://image.jtbcplus.kr/data/contents/jam_photo/202209/30/99275adb-c24b-4411-8d23-19f3f83a0f26.jpg"},{"title":"도산공원 주변 신상 맛집 3 (하퍼스바자 코리아 ─ 라이프스타일)","contents":"<!-- 2022-01-07 수정 -->\n                            <div class=\"imgbox Thumb455\" style=\"background-image: url('https://image.jtbcplus.kr/data/contents/jam_photo/202209/30/a9518c63-c601-4511-b1ce-ce8a6cc267be.jpg');\">\n                                <a href=\"/article/71237\">\n                                    <img alt=\"\" src=\"\">\n                                </a>\n                            </div>\n                            <!-- <div class=\"imgbox\">\n                                <a href=\"/article/\">\n                                    <img src=\"\" alt=\"\">\n                                </a>\n                            </div> -->\n                            <div class=\"textbox\">\n                                                        <em class=\"title\">\n                                    <a href=\"/article/71237\">\n                                        도산공원 주변 신상 맛집 3                                    </a>\n                                </em>\n                                <p class=\"excerpt\">걸어서 10분 거리에 미국식 고기 샌드위치, 뉴욕의 브런치 가게, 줄 서는 베이글 맛집이 생겼다...</p>\n                            </div>","link":"https://www.harpersbazaar.co.kr/article/71237","retrieved":1664550757448,"image":"https://image.jtbcplus.kr/data/contents/jam_photo/202209/30/a9518c63-c601-4511-b1ce-ce8a6cc267be.jpg"},{"title":"영화감독 래리 클락에게서 영감을 받은 공간? #뉴핫플레이스 (하퍼스바자 코리아 ─ 라이프스타일)","contents":"<!-- 2022-01-07 수정 -->\n                            <div class=\"imgbox Thumb455\" style=\"background-image: url('https://image.jtbcplus.kr/data/contents/jam_photo/202209/29/48ab1f4f-b905-4c47-9843-212b7ae28015.jpg');\">\n                                <a href=\"/article/71210\">\n                                    <img alt=\"\" src=\"\">\n                                </a>\n                            </div>\n                            <!-- <div class=\"imgbox\">\n                                <a href=\"/article/\">\n                                    <img src=\"\" alt=\"\">\n                                </a>\n                            </div> -->\n                            <div class=\"textbox\">\n                                                        <em class=\"title\">\n                                    <a href=\"/article/71210\">\n                                        영화감독 래리 클락에게서 영감을 받은 공간? #뉴핫플레이스                                    </a>\n                                </em>\n                                <p class=\"excerpt\">신상러들 모여라! 누구보다 발 빠르게 접수해야 할 뉴 핫플레이스.</p>\n                            </div>","link":"https://www.harpersbazaar.co.kr/article/71210","retrieved":1664550739690,"image":"https://image.jtbcplus.kr/data/contents/jam_photo/202209/29/48ab1f4f-b905-4c47-9843-212b7ae28015.jpg"},{"title":"과자 먹으면서 10KG 감량했다고? #다이어트두부과자 (하퍼스바자 코리아 ─ 라이프스타일)","contents":"<!-- 2022-01-07 수정 -->\n                            <div class=\"imgbox Thumb455\" style=\"background-image: url('https://image.jtbcplus.kr/data/contents/jam_photo/202209/29/c0be6ebb-b9de-4e1a-83aa-ca6d98109ef6.jpg');\">\n                                <a href=\"/article/71209\">\n                                    <img alt=\"\" src=\"\">\n                                </a>\n                            </div>\n                            <!-- <div class=\"imgbox\">\n                                <a href=\"/article/\">\n                                    <img src=\"\" alt=\"\">\n                                </a>\n                            </div> -->\n                            <div class=\"textbox\">\n                                                        <em class=\"title\">\n                                    <a href=\"/article/71209\">\n                                        과자 먹으면서 10KG 감량했다고? #다이어트두부과자                                    </a>\n                                </em>\n                                <p class=\"excerpt\">다이어터도 맘 놓고 즐기는 고단백 두부 과자 레시피! </p>\n                            </div>","link":"https://www.harpersbazaar.co.kr/article/71209","retrieved":1664550684958,"image":"https://image.jtbcplus.kr/data/contents/jam_photo/202209/29/c0be6ebb-b9de-4e1a-83aa-ca6d98109ef6.jpg"},{"title":"백종원이 강추하는 신박한 #샐러리레시피 (하퍼스바자 코리아 ─ 라이프스타일)","contents":"<div class=\"imgbox Thumb455\" style=\"background-image: url('https://image.jtbcplus.kr/data/contents/jam_photo/202209/29/cae226c6-537e-450a-be88-44b2ae27e2c0.jpg');\">\n                                <a href=\"/article/71208\">\n                                    <img alt=\"\" src=\"\">\n                                </a>\n                            </div>\n<!--                            <div class=\"imgbox\">-->\n<!--                                <a href=\"/article/--><!--\">-->\n<!--                                    <img src=\"--><!--\" alt=\"--><!--\">-->\n<!--                                </a>-->\n<!--                            </div>-->\n                            <div class=\"textbox\">\n                                                        <em class=\"title\">\n                                    <a href=\"/article/71208\">\n                                        백종원이 강추하는 신박한 #샐러리레시피                                    </a>\n                                </em>\n                                <p class=\"excerpt\">샐러리는 이렇게 먹는 거예요. 신박한 샐러리 레시피! </p>\n                            </div>","link":"https://www.harpersbazaar.co.kr/article/71208","retrieved":1664550739701,"image":"https://image.jtbcplus.kr/data/contents/jam_photo/202209/29/cae226c6-537e-450a-be88-44b2ae27e2c0.jpg"},{"title":"다이어터들의 식단 치트키 #토르티야레시피 (하퍼스바자 코리아 ─ 라이프스타일)","contents":"<div class=\"imgbox Thumb455\" style=\"background-image: url('https://image.jtbcplus.kr/data/contents/jam_photo/202209/29/de3fe2f9-c85e-4af7-8100-45b13f30bd8d.jpg');\">\n                                <a href=\"/article/71207\">\n                                    <img alt=\"\" src=\"\">\n                                </a>\n                            </div>\n<!--                            <div class=\"imgbox\">-->\n<!--                                <a href=\"/article/--><!--\">-->\n<!--                                    <img src=\"--><!--\" alt=\"--><!--\">-->\n<!--                                </a>-->\n<!--                            </div>-->\n                            <div class=\"textbox\">\n                                                        <em class=\"title\">\n                                    <a href=\"/article/71207\">\n                                        다이어터들의 식단 치트키 #토르티야레시피                                    </a>\n                                </em>\n                                <p class=\"excerpt\">저탄수 식단의 만능 치트키! 다이어트 좋은 토르티야 레시피.</p>\n                            </div>","link":"https://www.harpersbazaar.co.kr/article/71207","retrieved":1664513530168,"image":"https://image.jtbcplus.kr/data/contents/jam_photo/202209/29/de3fe2f9-c85e-4af7-8100-45b13f30bd8d.jpg"},{"title":"칼로리 완전 삭제시킨 #다이어트떡볶이 (하퍼스바자 코리아 ─ 라이프스타일)","contents":"<div class=\"imgbox Thumb455\" style=\"background-image: url('https://image.jtbcplus.kr/data/contents/jam_photo/202209/29/64a70e5f-8e10-4787-a0e9-164b3efc6dfa.jpg');\">\n                                <a href=\"/article/71139\">\n                                    <img alt=\"\" src=\"\">\n                                </a>\n                            </div>\n<!--                            <div class=\"imgbox\">-->\n<!--                                <a href=\"/article/--><!--\">-->\n<!--                                    <img src=\"--><!--\" alt=\"--><!--\">-->\n<!--                                </a>-->\n<!--                            </div>-->\n                            <div class=\"textbox\">\n                                                        <em class=\"title\">\n                                    <a href=\"/article/71139\">\n                                        칼로리 완전 삭제시킨 #다이어트떡볶이                                    </a>\n                                </em>\n                                <p class=\"excerpt\">이렇게 먹으면 안 쪄요. 다이어터도 안심하고 먹을 수 있는 떡볶이 레시피! </p>\n                            </div>","link":"https://www.harpersbazaar.co.kr/article/71139","retrieved":1664529602644,"image":"https://image.jtbcplus.kr/data/contents/jam_photo/202209/29/64a70e5f-8e10-4787-a0e9-164b3efc6dfa.jpg"},{"title":"김혜수, 조인성을 사로잡은 한효주의 #브라운치즈 디저트? (하퍼스바자 코리아 ─ 라이프스타일)","contents":"<div class=\"imgbox Thumb455\" style=\"background-image: url('https://image.jtbcplus.kr/data/contents/jam_photo/202209/29/b65ba1de-33e0-490c-901b-d5fc31fcb389.jpg');\">\n                                <a href=\"/article/71138\">\n                                    <img alt=\"\" src=\"\">\n                                </a>\n                            </div>\n<!--                            <div class=\"imgbox\">-->\n<!--                                <a href=\"/article/--><!--\">-->\n<!--                                    <img src=\"--><!--\" alt=\"--><!--\">-->\n<!--                                </a>-->\n<!--                            </div>-->\n                            <div class=\"textbox\">\n                                                        <em class=\"title\">\n                                    <a href=\"/article/71138\">\n                                        김혜수, 조인성을 사로잡은 한효주의 #브라운치즈 디저트?                                     </a>\n                                </em>\n                                <p class=\"excerpt\">한번 맛보면 탈출구는 없다. 단짠단짠 묘한 매력의 브라운 치즈 활용 레시피! </p>\n                            </div>","link":"https://www.harpersbazaar.co.kr/article/71138","retrieved":1664513547286,"image":"https://image.jtbcplus.kr/data/contents/jam_photo/202209/29/b65ba1de-33e0-490c-901b-d5fc31fcb389.jpg"},{"title":"일회용기보다 다회용기가 더 깨끗하다고? (하퍼스바자 코리아 ─ 지속가능성)","contents":"<!-- 2022-01-07 수정 -->\n                            <div class=\"imgbox Thumb455\" style=\"background-image: url('https://image.jtbcplus.kr/data/contents/jam_photo/202209/01/3e6c7a2c-36f7-4060-b40a-7346c754364e.jpg');\">\n                                <a href=\"/article/70156\">\n                                    <img alt=\"\" src=\"\">\n                                </a>\n                            </div>\n                            <!-- <div class=\"imgbox\">\n                                <a href=\"/article/\">\n                                    <img src=\"\" alt=\"\">\n                                </a>\n                            </div> -->\n                            <div class=\"textbox\">\n                                                        <em class=\"title\">\n                                    <a href=\"/article/70156\">\n                                        일회용기보다 다회용기가 더 깨끗하다고?                                     </a>\n                                </em>\n                                <p class=\"excerpt\">트래쉬버스터즈는 다회용 식기를 대여하는 서비스 업체다. 카페, 영화관, 행사장 등 일회용품을 ...</p>\n                            </div>","link":"https://www.harpersbazaar.co.kr/article/70156","retrieved":1663233229764,"image":"https://image.jtbcplus.kr/data/contents/jam_photo/202209/01/3e6c7a2c-36f7-4060-b40a-7346c754364e.jpg"},{"title":"향기로운 ‘친환경’ 추석선물 3 (하퍼스바자 코리아 ─ 지속가능성)","contents":"<!-- 2022-01-07 수정 -->\n                            <div class=\"imgbox Thumb455\" style=\"background-image: url('https://image.jtbcplus.kr/data/contents/jam_photo/202208/19/ff642044-301b-4e19-9bf0-ca780ecf72bb.jpg');\">\n                                <a href=\"/article/68923\">\n                                    <img alt=\"\" src=\"\">\n                                </a>\n                            </div>\n                            <!-- <div class=\"imgbox\">\n                                <a href=\"/article/\">\n                                    <img src=\"\" alt=\"\">\n                                </a>\n                            </div> -->\n                            <div class=\"textbox\">\n                                                        <em class=\"title\">\n                                    <a href=\"/article/68923\">\n                                        향기로운 ‘친환경’ 추석선물 3                                     </a>\n                                </em>\n                                <p class=\"excerpt\">환경을 생각하는 아이템으로 감사한 마음을 전해보세요.</p>\n                            </div>","link":"https://www.harpersbazaar.co.kr/article/68923","retrieved":1662632379640,"image":"https://image.jtbcplus.kr/data/contents/jam_photo/202208/19/ff642044-301b-4e19-9bf0-ca780ecf72bb.jpg"},{"title":"요즘 환경을 생각한 패션 브랜드는 폐기된 의류에서 소재를 얻는다고? (하퍼스바자 코리아 ─ 지속가능성)","contents":"<!-- 2022-01-07 수정 -->\n                            <div class=\"imgbox Thumb455\" style=\"background-image: url('https://image.jtbcplus.kr/data/contents/jam_photo/202208/11/7a5b333a-2c45-47e3-ad78-06194b4a6015.jpg');\">\n                                <a href=\"/article/68775\">\n                                    <img alt=\"\" src=\"\">\n                                </a>\n                            </div>\n                            <!-- <div class=\"imgbox\">\n                                <a href=\"/article/\">\n                                    <img src=\"\" alt=\"\">\n                                </a>\n                            </div> -->\n                            <div class=\"textbox\">\n                                                        <em class=\"title\">\n                                    <a href=\"/article/68775\">\n                                        요즘 환경을 생각한 패션 브랜드는 폐기된 의류에서 소재를 얻는다고?                                    </a>\n                                </em>\n                                <p class=\"excerpt\">버려지는 의류에서 추출한 염료, 신소재로 만든 판가이아, 자라의 캡슐 컬렉션</p>\n                            </div>","link":"https://www.harpersbazaar.co.kr/article/68775","retrieved":1662398652920,"image":"https://image.jtbcplus.kr/data/contents/jam_photo/202208/11/7a5b333a-2c45-47e3-ad78-06194b4a6015.jpg"},{"title":"여러분의 스리라차 소스가 마트에서 사라집니다 (하퍼스바자 코리아 ─ 지속가능성)","contents":"<!-- 2022-01-07 수정 -->\n                            <div class=\"imgbox Thumb455\" style=\"background-image: url('https://image.jtbcplus.kr/data/contents/jam_photo/202208/06/5e0d70ca-6be4-4acc-a21d-5ba55dcda81a.jpg');\">\n                                <a href=\"/article/68383\">\n                                    <img alt=\"\" src=\"\">\n                                </a>\n                            </div>\n                            <!-- <div class=\"imgbox\">\n                                <a href=\"/article/\">\n                                    <img src=\"\" alt=\"\">\n                                </a>\n                            </div> -->\n                            <div class=\"textbox\">\n                                                        <em class=\"title\">\n                                    <a href=\"/article/68383\">\n                                        여러분의 스리라차 소스가 마트에서 사라집니다                                     </a>\n                                </em>\n                                <p class=\"excerpt\">연간 2천만 병 생산되는 후이퐁(Huy Fong) 스리라차 소스가 오는 9월까지 약 6개월간 생산을 중...</p>\n                            </div>","link":"https://www.harpersbazaar.co.kr/article/68383","retrieved":1662322650586,"image":"https://image.jtbcplus.kr/data/contents/jam_photo/202208/06/5e0d70ca-6be4-4acc-a21d-5ba55dcda81a.jpg"},{"title":"그린슈머들이 첫 제품으로 많이 사용하는 이것은? (하퍼스바자 코리아 ─ 지속가능성)","contents":"<div class=\"imgbox Thumb455\" style=\"background-image: url('https://image.jtbcplus.kr/data/contents/jam_photo/202208/01/51632ff3-75d0-40cb-b23c-72712a1aeb98.jpg');\">\n                                <a href=\"/article/68516\">\n                                    <img alt=\"\" src=\"\">\n                                </a>\n                            </div>\n<!--                            <div class=\"imgbox\">-->\n<!--                                <a href=\"/article/--><!--\">-->\n<!--                                    <img src=\"--><!--\" alt=\"--><!--\">-->\n<!--                                </a>-->\n<!--                            </div>-->\n                            <div class=\"textbox\">\n                                                        <em class=\"title\">\n                                    <a href=\"/article/68516\">\n                                        그린슈머들이 첫 제품으로 많이 사용하는 이것은?                                    </a>\n                                </em>\n                                <p class=\"excerpt\">지구와 친해지고 싶다면 바로 이 제품부터! </p>\n                            </div>","link":"https://www.harpersbazaar.co.kr/article/68516","retrieved":1662146177595,"image":"https://image.jtbcplus.kr/data/contents/jam_photo/202208/01/51632ff3-75d0-40cb-b23c-72712a1aeb98.jpg"},{"title":"동해 바다에서 플로깅하고 공짜로 과자 먹는 방법은? #씨낵 (하퍼스바자 코리아 ─ 지속가능성)","contents":"<div class=\"imgbox Thumb455\" style=\"background-image: url('https://image.jtbcplus.kr/data/contents/jam_photo/202207/22/b1ab64fd-9cd1-46dc-ab1d-a816fc9b852e.jpg');\">\n                                <a href=\"/article/68202\">\n                                    <img alt=\"\" src=\"\">\n                                </a>\n                            </div>\n<!--                            <div class=\"imgbox\">-->\n<!--                                <a href=\"/article/--><!--\">-->\n<!--                                    <img src=\"--><!--\" alt=\"--><!--\">-->\n<!--                                </a>-->\n<!--                            </div>-->\n                            <div class=\"textbox\">\n                                                        <em class=\"title\">\n                                    <a href=\"/article/68202\">\n                                        동해 바다에서 플로깅하고 공짜로 과자 먹는 방법은? #씨낵                                    </a>\n                                </em>\n                                <p class=\"excerpt\">바다 쓰레기 주우면 과자 드려요! 쇼미더과자! </p>\n                            </div>","link":"https://www.harpersbazaar.co.kr/article/68202","retrieved":1661984354745,"image":"https://image.jtbcplus.kr/data/contents/jam_photo/202207/22/b1ab64fd-9cd1-46dc-ab1d-a816fc9b852e.jpg"},{"title":"'논-비건'의 입맛을 사로잡은 신상 비건 식당 2 (하퍼스바자 코리아 ─ 지속가능성)","contents":"<div class=\"imgbox Thumb455\" style=\"background-image: url('https://image.jtbcplus.kr/data/contents/jam_photo/202207/13/94a87ee7-8cb8-4050-af18-752b3f45bb09.jpg');\">\n                                <a href=\"/article/67955\">\n                                    <img alt=\"\" src=\"\">\n                                </a>\n                            </div>\n<!--                            <div class=\"imgbox\">-->\n<!--                                <a href=\"/article/--><!--\">-->\n<!--                                    <img src=\"--><!--\" alt=\"--><!--\">-->\n<!--                                </a>-->\n<!--                            </div>-->\n                            <div class=\"textbox\">\n                                                        <em class=\"title\">\n                                    <a href=\"/article/67955\">\n                                        '논-비건'의 입맛을 사로잡은 신상 비건 식당 2                                    </a>\n                                </em>\n                                <p class=\"excerpt\">맛있는 음식으로 지구를 위한 가치 소비를 실천해보자! </p>\n                            </div>","link":"https://www.harpersbazaar.co.kr/article/67955","retrieved":1660830078420,"image":"https://image.jtbcplus.kr/data/contents/jam_photo/202207/13/94a87ee7-8cb8-4050-af18-752b3f45bb09.jpg"},{"title":"디지털 크리에이터 리나와 <바자>의 특별한 만남! (하퍼스바자 코리아 ─ 지속가능성)","contents":"<div class=\"imgbox Thumb455\" style=\"background-image: url('https://image.jtbcplus.kr/data/contents/jam_photo/202206/30/e5a3dc5f-808f-4b70-a0b4-4c174d7aa5cc.jpg');\">\n                                <a href=\"/article/67484\">\n                                    <img alt=\"\" src=\"\">\n                                </a>\n                            </div>\n<!--                            <div class=\"imgbox\">-->\n<!--                                <a href=\"/article/--><!--\">-->\n<!--                                    <img src=\"--><!--\" alt=\"--><!--\">-->\n<!--                                </a>-->\n<!--                            </div>-->\n                            <div class=\"textbox\">\n                                                        <em class=\"title\">\n                                    <a href=\"/article/67484\">\n                                        디지털 크리에이터 리나와 &lt;바자&gt;의 특별한 만남!                                     </a>\n                                </em>\n                                <p class=\"excerpt\">시작을 어려워 하는 사람들을 위해 리나가 준비한 옷의 새 주인 찾기 #옷찾사</p>\n                            </div>","link":"https://www.harpersbazaar.co.kr/article/67484","retrieved":1660198754015,"image":"https://image.jtbcplus.kr/data/contents/jam_photo/202206/30/e5a3dc5f-808f-4b70-a0b4-4c174d7aa5cc.jpg"}]}