{"title":"하퍼스바자 코리아 ─ 아트&컬쳐","url":"https://www.harpersbazaar.co.kr/artandculture","favicon":"https://www.harpersbazaar.co.kr/favicon.ico","elements":[{"title":"역대급 노출 수위로 난리 난 마릴린 먼로의 영화?","contents":"<!-- 2022-01-07 수정 -->\n                            <div class=\"imgbox Thumb455\" style=\"background-image: url('https://image.jtbcplus.kr/data/contents/jam_photo/202210/17/665d5759-8db7-4068-bdc5-022038d29793.jpg');\">\n                                <a href=\"/article/71624\">\n                                    <img alt=\"\" src=\"\">\n                                </a>\n                            </div>\n                            <!-- <div class=\"imgbox\">\n                                <a href=\"/article/\">\n                                    <img src=\"\" alt=\"\">\n                                </a>\n                            </div> -->\n                            <div class=\"textbox\">\n                                                        <em class=\"title\">\n                                    <a href=\"/article/71624\">\n                                        역대급 노출 수위로 난리 난 마릴린 먼로의 영화?                                     </a>\n                                </em>\n                                <p class=\"excerpt\">뜨거운 감자로 떠오른 영화 &lt;블론드&gt;. 도대체 어떤 작품이길래?</p>\n                            </div>","link":"https://www.harpersbazaar.co.kr/article/71624","retrieved":1666257590186,"image":"https://image.jtbcplus.kr/data/contents/jam_photo/202210/17/665d5759-8db7-4068-bdc5-022038d29793.jpg"},{"title":"해외 대세 아티스트는? 세계 곳곳의 갤러리스트에게 물어본 자국의 아트신","contents":"<!-- 2022-01-07 수정 -->\n                            <div class=\"imgbox Thumb455\" style=\"background-image: url('https://image.jtbcplus.kr/data/contents/jam_photo/202210/17/890a5164-ffb3-4a3c-9d8d-42d7a1cd8076.jpg');\">\n                                <a href=\"/article/71367\">\n                                    <img alt=\"\" src=\"\">\n                                </a>\n                            </div>\n                            <!-- <div class=\"imgbox\">\n                                <a href=\"/article/\">\n                                    <img src=\"\" alt=\"\">\n                                </a>\n                            </div> -->\n                            <div class=\"textbox\">\n                                                        <em class=\"title\">\n                                    <a href=\"/article/71367\">\n                                        해외 대세 아티스트는? 세계 곳곳의 갤러리스트에게 물어본 자국의 아트신                                     </a>\n                                </em>\n                                <p class=\"excerpt\">세계 곳곳에 위치한 로컬 갤러리의 갤러리스트에게 자국의 아트 신에 대해 물었다.</p>\n                            </div>","link":"https://www.harpersbazaar.co.kr/article/71367","retrieved":1666192454764,"image":"https://image.jtbcplus.kr/data/contents/jam_photo/202210/17/890a5164-ffb3-4a3c-9d8d-42d7a1cd8076.jpg"},{"title":"영감을 안겨줄 카페 5 곳!","contents":"<!-- 2022-01-07 수정 -->\n                            <div class=\"imgbox Thumb455\" style=\"background-image: url('https://image.jtbcplus.kr/data/contents/jam_photo/202210/16/763b9f55-c574-4c58-b911-8ae8bbf641b6.jpg');\">\n                                <a href=\"/article/71364\">\n                                    <img alt=\"\" src=\"\">\n                                </a>\n                            </div>\n                            <!-- <div class=\"imgbox\">\n                                <a href=\"/article/\">\n                                    <img src=\"\" alt=\"\">\n                                </a>\n                            </div> -->\n                            <div class=\"textbox\">\n                                                        <em class=\"title\">\n                                    <a href=\"/article/71364\">\n                                        영감을 안겨줄 카페 5 곳!                                    </a>\n                                </em>\n                                <p class=\"excerpt\">전시장 사이를 오가는 관람객에게 예술의 여운을 선사하는 미술관 카페.</p>\n                            </div>","link":"https://www.harpersbazaar.co.kr/article/71364","retrieved":1666084753240,"image":"https://image.jtbcplus.kr/data/contents/jam_photo/202210/16/763b9f55-c574-4c58-b911-8ae8bbf641b6.jpg"},{"title":"모두 깜짝 놀란 (여자)아이들, '누드' MV 티저","contents":"<!-- 2022-01-07 수정 -->\n                            <div class=\"imgbox Thumb455\" style=\"background-image: url('https://image.jtbcplus.kr/data/contents/jam_photo/202210/15/8e64dabe-63a3-46d2-adb2-46abb2b85ac8.jpg');\">\n                                <a href=\"/article/71586\">\n                                    <img alt=\"\" src=\"\">\n                                </a>\n                            </div>\n                            <!-- <div class=\"imgbox\">\n                                <a href=\"/article/\">\n                                    <img src=\"\" alt=\"\">\n                                </a>\n                            </div> -->\n                            <div class=\"textbox\">\n                                                        <em class=\"title\">\n                                    <a href=\"/article/71586\">\n                                        모두 깜짝 놀란 (여자)아이들, '누드' MV 티저                                    </a>\n                                </em>\n                                <p class=\"excerpt\">\"정말 모든 걸 벗었다\".. 이것은 도발 그 잡채!</p>\n                            </div>","link":"https://www.harpersbazaar.co.kr/article/71586","retrieved":1666084753242,"image":"https://image.jtbcplus.kr/data/contents/jam_photo/202210/15/8e64dabe-63a3-46d2-adb2-46abb2b85ac8.jpg"},{"title":"예술가 듀오의 쥬얼리","contents":"<div class=\"imgbox Thumb455\" style=\"background-image: url('https://image.jtbcplus.kr/data/contents/jam_photo/202210/15/ae66e7a7-00c6-4d9e-9039-518e9b8062e2.jpg');\">\n                                <a href=\"/article/71363\">\n                                    <img alt=\"\" src=\"\">\n                                </a>\n                            </div>\n<!--                            <div class=\"imgbox\">-->\n<!--                                <a href=\"/article/--><!--\">-->\n<!--                                    <img src=\"--><!--\" alt=\"--><!--\">-->\n<!--                                </a>-->\n<!--                            </div>-->\n                            <div class=\"textbox\">\n                                                        <em class=\"title\">\n                                    <a href=\"/article/71363\">\n                                        예술가 듀오의 쥬얼리                                    </a>\n                                </em>\n                                <p class=\"excerpt\">비디오 아티스트 나탈리 뒤버그(Nathalie Djurberg)와 음악가 한스 버그(Hans Berg)는 이 시대의 ...</p>\n                            </div>","link":"https://www.harpersbazaar.co.kr/article/71363","retrieved":1666019643083,"image":"https://image.jtbcplus.kr/data/contents/jam_photo/202210/15/ae66e7a7-00c6-4d9e-9039-518e9b8062e2.jpg"},{"title":"요즘 SNS에서 난리 난 신박한 컵라면 요리!","contents":"<div class=\"imgbox Thumb455\" style=\"background-image: url('https://image.jtbcplus.kr/data/contents/jam_photo/202210/14/8497ff78-0d6e-4f8e-8cf3-30d58466d06c.jpg');\">\n                                <a href=\"/article/71578\">\n                                    <img alt=\"\" src=\"\">\n                                </a>\n                            </div>\n<!--                            <div class=\"imgbox\">-->\n<!--                                <a href=\"/article/--><!--\">-->\n<!--                                    <img src=\"--><!--\" alt=\"--><!--\">-->\n<!--                                </a>-->\n<!--                            </div>-->\n                            <div class=\"textbox\">\n                                                        <em class=\"title\">\n                                    <a href=\"/article/71578\">\n                                        요즘 SNS에서 난리 난 신박한 컵라면 요리!                                     </a>\n                                </em>\n                                <p class=\"excerpt\">컵라면 어디까지 먹어 봤니? 초간단 이색 컵라면 레시피! </p>\n                            </div>","link":"https://www.harpersbazaar.co.kr/article/71578","retrieved":1666019643086,"image":"https://image.jtbcplus.kr/data/contents/jam_photo/202210/14/8497ff78-0d6e-4f8e-8cf3-30d58466d06c.jpg"},{"title":"넷플릭스, 뮤직쇼도 성공할까? '넘사벽' 스케일 <테이크 원>","contents":"<div class=\"imgbox Thumb455\" style=\"background-image: url('https://image.jtbcplus.kr/data/contents/jam_photo/202210/14/5c7ff130-6549-4e5f-887b-0224cd640a60.jpg');\">\n                                <a href=\"/article/71569\">\n                                    <img alt=\"\" src=\"\">\n                                </a>\n                            </div>\n<!--                            <div class=\"imgbox\">-->\n<!--                                <a href=\"/article/--><!--\">-->\n<!--                                    <img src=\"--><!--\" alt=\"--><!--\">-->\n<!--                                </a>-->\n<!--                            </div>-->\n                            <div class=\"textbox\">\n                                                        <em class=\"title\">\n                                    <a href=\"/article/71569\">\n                                        넷플릭스, 뮤직쇼도 성공할까? '넘사벽' 스케일 &lt;테이크 원&gt;                                    </a>\n                                </em>\n                                <p class=\"excerpt\">조수미부터 임재범·비·악뮤·마마무.. hot 라인업+어마무시 스케일</p>\n                            </div>","link":"https://www.harpersbazaar.co.kr/article/71569","retrieved":1665932588473,"image":"https://image.jtbcplus.kr/data/contents/jam_photo/202210/14/5c7ff130-6549-4e5f-887b-0224cd640a60.jpg"},{"title":"종이호일만 있으면 끝, 강민경이 추천하는 #파피요트레시피","contents":"<div class=\"imgbox Thumb455\" style=\"background-image: url('https://image.jtbcplus.kr/data/contents/jam_photo/202210/14/93e86a81-ddae-47b9-9654-55a9da8ec136.jpg');\">\n                                <a href=\"/article/71567\">\n                                    <img alt=\"\" src=\"\">\n                                </a>\n                            </div>\n<!--                            <div class=\"imgbox\">-->\n<!--                                <a href=\"/article/--><!--\">-->\n<!--                                    <img src=\"--><!--\" alt=\"--><!--\">-->\n<!--                                </a>-->\n<!--                            </div>-->\n                            <div class=\"textbox\">\n                                                        <em class=\"title\">\n                                    <a href=\"/article/71567\">\n                                        종이호일만 있으면 끝, 강민경이 추천하는 #파피요트레시피                                    </a>\n                                </em>\n                                <p class=\"excerpt\">진짜 간단하고 설거지거리도 안 나온다. 쉽고 있어 보이는 파피요트 레시피! </p>\n                            </div>","link":"https://www.harpersbazaar.co.kr/article/71567","retrieved":1665846212552,"image":"https://image.jtbcplus.kr/data/contents/jam_photo/202210/14/93e86a81-ddae-47b9-9654-55a9da8ec136.jpg"}]}