{"title":"하퍼스바자 코리아 ─ 뷰티","url":"https://www.harpersbazaar.co.kr/beauty","favicon":"https://www.harpersbazaar.co.kr/favicon.ico","elements":[{"title":"또렷하고 똘망한 눈매를 만드는 방법","contents":"<!-- 2022-01-07 수정 -->\n                            <div class=\"imgbox Thumb455\" style=\"background-image: url('https://image.jtbcplus.kr/data/contents/jam_photo/202209/08/2d90ef76-b813-40a4-8992-f20765a982e4.jpg');\">\n                                <a href=\"/article/70307\">\n                                    <img alt=\"\" src=\"\">\n                                </a>\n                            </div>\n                            <!-- <div class=\"imgbox\">\n                                <a href=\"/article/\">\n                                    <img src=\"\" alt=\"\">\n                                </a>\n                            </div> -->\n                            <div class=\"textbox\">\n                                                        <em class=\"title\">\n                                    <a href=\"/article/70307\">\n                                        또렷하고 똘망한 눈매를 만드는 방법                                    </a>\n                                </em>\n                                <p class=\"excerpt\">바자가 엄선한 메이크업 신제품으로 가능! </p>\n                            </div>","link":"https://www.harpersbazaar.co.kr/article/70307","retrieved":1662826780945,"image":"https://image.jtbcplus.kr/data/contents/jam_photo/202209/08/2d90ef76-b813-40a4-8992-f20765a982e4.jpg"},{"title":"다이어트 전문가가 말하는 추석 후 다이어트","contents":"<!-- 2022-01-07 수정 -->\n                            <div class=\"imgbox Thumb455\" style=\"background-image: url('https://image.jtbcplus.kr/data/contents/jam_photo/202209/07/cf39d288-69f4-4bd9-b73c-a6d327b42c06.jpg');\">\n                                <a href=\"/article/70564\">\n                                    <img alt=\"\" src=\"\">\n                                </a>\n                            </div>\n                            <!-- <div class=\"imgbox\">\n                                <a href=\"/article/\">\n                                    <img src=\"\" alt=\"\">\n                                </a>\n                            </div> -->\n                            <div class=\"textbox\">\n                                                        <em class=\"title\">\n                                    <a href=\"/article/70564\">\n                                         다이어트 전문가가 말하는 추석 후 다이어트                                      </a>\n                                </em>\n                                <p class=\"excerpt\">진짜 살 되기 전에 비워 내야죠</p>\n                            </div>","link":"https://www.harpersbazaar.co.kr/article/70564","retrieved":1662740574384,"image":"https://image.jtbcplus.kr/data/contents/jam_photo/202209/07/cf39d288-69f4-4bd9-b73c-a6d327b42c06.jpg"},{"title":"아이 메이크업이 어렵다면 따라와!","contents":"<!-- 2022-01-07 수정 -->\n                            <div class=\"imgbox Thumb455\" style=\"background-image: url('https://image.jtbcplus.kr/data/contents/jam_photo/202209/08/e52fa9f0-a3ad-431f-b7ca-500dc6c57a77.jpg');\">\n                                <a href=\"/article/70361\">\n                                    <img alt=\"\" src=\"\">\n                                </a>\n                            </div>\n                            <!-- <div class=\"imgbox\">\n                                <a href=\"/article/\">\n                                    <img src=\"\" alt=\"\">\n                                </a>\n                            </div> -->\n                            <div class=\"textbox\">\n                                                        <em class=\"title\">\n                                    <a href=\"/article/70361\">\n                                        아이 메이크업이 어렵다면 따라와!                                    </a>\n                                </em>\n                                <p class=\"excerpt\">샤넬 레 꺄트르 옹브르 트위드로 완성하는 뷰티 룩</p>\n                            </div>","link":"https://www.harpersbazaar.co.kr/article/70361","retrieved":1662740574387,"image":"https://image.jtbcplus.kr/data/contents/jam_photo/202209/08/e52fa9f0-a3ad-431f-b7ca-500dc6c57a77.jpg"},{"title":"건성부터 지성까지 쓸 수 있는 윤기 파운데이션","contents":"<!-- 2022-01-07 수정 -->\n                            <div class=\"imgbox Thumb455\" style=\"background-image: url('https://image.jtbcplus.kr/data/contents/jam_photo/202209/06/16f62365-b2ec-485b-9782-adbdc4164373.jpg');\">\n                                <a href=\"/article/70305\">\n                                    <img alt=\"\" src=\"\">\n                                </a>\n                            </div>\n                            <!-- <div class=\"imgbox\">\n                                <a href=\"/article/\">\n                                    <img src=\"\" alt=\"\">\n                                </a>\n                            </div> -->\n                            <div class=\"textbox\">\n                                                        <em class=\"title\">\n                                    <a href=\"/article/70305\">\n                                        건성부터 지성까지 쓸 수 있는 윤기 파운데이션                                    </a>\n                                </em>\n                                <p class=\"excerpt\">건조하지 않은데 커버력도 좋은 신상 베이스</p>\n                            </div>","link":"https://www.harpersbazaar.co.kr/article/70305","retrieved":1662740574389,"image":"https://image.jtbcplus.kr/data/contents/jam_photo/202209/06/16f62365-b2ec-485b-9782-adbdc4164373.jpg"},{"title":"뉴진스, 이하이가 즐겨하는 보석 메이크업의 비밀","contents":"<div class=\"imgbox Thumb455\" style=\"background-image: url('https://image.jtbcplus.kr/data/contents/jam_photo/202209/08/b8d2e725-9965-44b9-a7ca-33a668970a6e.jpg');\">\n                                <a href=\"/article/70460\">\n                                    <img alt=\"\" src=\"\">\n                                </a>\n                            </div>\n<!--                            <div class=\"imgbox\">-->\n<!--                                <a href=\"/article/--><!--\">-->\n<!--                                    <img src=\"--><!--\" alt=\"--><!--\">-->\n<!--                                </a>-->\n<!--                            </div>-->\n                            <div class=\"textbox\">\n                                                        <em class=\"title\">\n                                    <a href=\"/article/70460\">\n                                        뉴진스, 이하이가 즐겨하는 보석 메이크업의 비밀                                    </a>\n                                </em>\n                                <p class=\"excerpt\">보석 메이크업 도전하고 싶다면 클릭!</p>\n                            </div>","link":"https://www.harpersbazaar.co.kr/article/70460","retrieved":1662661098110,"image":"https://image.jtbcplus.kr/data/contents/jam_photo/202209/08/b8d2e725-9965-44b9-a7ca-33a668970a6e.jpg"},{"title":"신상 보러갈래? 립스틱 맛집에 신제품 들어왔대","contents":"<div class=\"imgbox Thumb455\" style=\"background-image: url('https://image.jtbcplus.kr/data/contents/jam_photo/202209/05/be0979e0-2922-40de-9730-8a9614490108.jpg');\">\n                                <a href=\"/article/70304\">\n                                    <img alt=\"\" src=\"\">\n                                </a>\n                            </div>\n<!--                            <div class=\"imgbox\">-->\n<!--                                <a href=\"/article/--><!--\">-->\n<!--                                    <img src=\"--><!--\" alt=\"--><!--\">-->\n<!--                                </a>-->\n<!--                            </div>-->\n                            <div class=\"textbox\">\n                                                        <em class=\"title\">\n                                    <a href=\"/article/70304\">\n                                        신상 보러갈래? 립스틱 맛집에 신제품 들어왔대                                    </a>\n                                </em>\n                                <p class=\"excerpt\">맥, 샤넬, 입생로랑, 아르마니까지!</p>\n                            </div>","link":"https://www.harpersbazaar.co.kr/article/70304","retrieved":1662578188944,"image":"https://image.jtbcplus.kr/data/contents/jam_photo/202209/05/be0979e0-2922-40de-9730-8a9614490108.jpg"},{"title":"브랜드가 이 갈고 만든 스킨케어 신제품","contents":"<div class=\"imgbox Thumb455\" style=\"background-image: url('https://image.jtbcplus.kr/data/contents/jam_photo/202209/04/e534a4ec-7f44-401c-ab5f-160d548bc845.jpg');\">\n                                <a href=\"/article/70303\">\n                                    <img alt=\"\" src=\"\">\n                                </a>\n                            </div>\n<!--                            <div class=\"imgbox\">-->\n<!--                                <a href=\"/article/--><!--\">-->\n<!--                                    <img src=\"--><!--\" alt=\"--><!--\">-->\n<!--                                </a>-->\n<!--                            </div>-->\n                            <div class=\"textbox\">\n                                                        <em class=\"title\">\n                                    <a href=\"/article/70303\">\n                                        브랜드가 이 갈고 만든 스킨케어 신제품                                    </a>\n                                </em>\n                                <p class=\"excerpt\">요즘 핫하다고 소문난 제품을 모두 모았다</p>\n                            </div>","link":"https://www.harpersbazaar.co.kr/article/70303","retrieved":1662542305851,"image":"https://image.jtbcplus.kr/data/contents/jam_photo/202209/04/e534a4ec-7f44-401c-ab5f-160d548bc845.jpg"},{"title":"‘요즘’ 스러운 거울 셀카 찍는 법","contents":"<div class=\"imgbox Thumb455\" style=\"background-image: url('https://image.jtbcplus.kr/data/contents/jam_photo/202209/02/30a1e1bc-7def-47e3-b0f4-b67751de6bfa.jpg');\">\n                                <a href=\"/article/70424\">\n                                    <img alt=\"\" src=\"\">\n                                </a>\n                            </div>\n<!--                            <div class=\"imgbox\">-->\n<!--                                <a href=\"/article/--><!--\">-->\n<!--                                    <img src=\"--><!--\" alt=\"--><!--\">-->\n<!--                                </a>-->\n<!--                            </div>-->\n                            <div class=\"textbox\">\n                                                        <em class=\"title\">\n                                    <a href=\"/article/70424\">\n                                         ‘요즘’ 스러운 거울 셀카 찍는 법                                     </a>\n                                </em>\n                                <p class=\"excerpt\">사진 찍을 때마다 갈 길 잃는 손, 왠지 모르게 어색한 포즈 이렇게 수습하자</p>\n                            </div>","link":"https://www.harpersbazaar.co.kr/article/70424","retrieved":1662484998706,"image":"https://image.jtbcplus.kr/data/contents/jam_photo/202209/02/30a1e1bc-7def-47e3-b0f4-b67751de6bfa.jpg"}]}